[
  {
    "bookingId": "9332656800",
    "dateOfBirth": "1988-4-17",
    "ethnicity": "Aranea",
    "firstName": "Savannah",
    "gender": "Demi-man",
    "indeterminateSentence": true,
    "lastName": "Fritsch",
    "prisonName": "County Tyrone (HMP)",
    "prisonerNumber": "Y7RLN5A",
    "religion": "Pel",
    "sentenceExpiryDate": "2034-12-20"
  },
  {
    "bookingId": "7345105758",
    "dateOfBirth": "1994-8-13",
    "ethnicity": "Coepi",
    "firstName": "Kallie",
    "gender": "Cisgender female",
    "homeDetentionCurfewEligibilityDate": "2030-11-25",
    "lastName": "Lakin",
    "paroleEligibilityDate": "2038-03-08",
    "prisonName": "East Sussex (HMP)",
    "prisonerNumber": "175AQ4D",
    "religion": "Cunabula",
    "sentenceExpiryDate": "2043-02-15",
    "sentenceStartDate": "Tue Dec 11",
    "tariffDate": "2025-03-04"
  },
  {
    "bookingId": "8592169147",
    "conditionalReleaseDate": "2026-11-06",
    "dateOfBirth": "1969-2-23",
    "ethnicity": "Alter",
    "firstName": "Jesus",
    "gender": "T* man",
    "homeDetentionCurfewEligibilityDate": "2030-04-18",
    "indeterminateSentence": true,
    "lastName": "Tromp",
    "prisonName": "Mid Glamorgan (HMP)",
    "prisonerNumber": "TXWAMYX",
    "religion": "Arcus",
    "sentenceExpiryDate": "2037-02-06",
    "sentenceStartDate": "Fri Jan 22",
    "tariffDate": "2026-09-06"
  },
  {
    "bookingId": "1852862949",
    "conditionalReleaseDate": "2032-02-05",
    "dateOfBirth": "1959-8-14",
    "ethnicity": "Adduco",
    "firstName": "Hunter",
    "gender": "Gender variant",
    "lastName": "Schultz",
    "prisonName": "Hertfordshire (HMP)",
    "prisonerNumber": "D7C2BPQ",
    "religion": "Eos",
    "sentenceExpiryDate": "2029-11-14",
    "sentenceStartDate": "Sun Aug 06"
  },
  {
    "bookingId": "6783951444",
    "conditionalReleaseDate": "2032-04-04",
    "dateOfBirth": "1993-3-16",
    "ethnicity": "Coaegresco",
    "firstName": "Marina",
    "gender": "Genderflux",
    "lastName": "Hermiston",
    "prisonName": "County Down (HMP)",
    "prisonerNumber": "439P14J",
    "religion": "Absque",
    "sentenceStartDate": "Wed Jan 23",
    "tariffDate": "2034-06-14"
  },
  {
    "bookingId": "7156408729",
    "conditionalReleaseDate": "2033-06-16",
    "dateOfBirth": "1946-6-21",
    "ethnicity": "Cicuta",
    "firstName": "Sallie",
    "gender": "Cisgender man",
    "lastName": "Frami",
    "paroleEligibilityDate": "2034-10-15",
    "prisonName": "Somerset (HMP)",
    "prisonerNumber": "S8M1LGC",
    "religion": "Solvo",
    "sentenceExpiryDate": "2035-01-07",
    "tariffDate": "2040-11-16"
  },
  {
    "bookingId": "1918337781",
    "dateOfBirth": "1976-11-23",
    "ethnicity": "Vulnero",
    "firstName": "Reyna",
    "gender": "Neutrois",
    "homeDetentionCurfewEligibilityDate": "2027-05-28",
    "lastName": "Zboncak",
    "paroleEligibilityDate": "2025-08-30",
    "prisonName": "South Glamorgan (HMP)",
    "prisonerNumber": "B9C83GE",
    "religion": "Virtus",
    "sentenceExpiryDate": "2042-06-23"
  },
  {
    "bookingId": "4072445675",
    "dateOfBirth": "1968-5-10",
    "ethnicity": "Vicissitudo",
    "firstName": "Kallie",
    "gender": "Trans person",
    "homeDetentionCurfewEligibilityDate": "2024-06-04",
    "lastName": "Braun",
    "paroleEligibilityDate": "2043-06-04",
    "prisonName": "Avon (HMP)",
    "prisonerNumber": "VXKGG1D",
    "religion": "Undique",
    "sentenceStartDate": "Tue Oct 24",
    "tariffDate": "2033-02-16"
  },
  {
    "bookingId": "8039579339",
    "dateOfBirth": "1999-3-23",
    "ethnicity": "Ara",
    "firstName": "Julia",
    "gender": "Xenogender",
    "indeterminateSentence": false,
    "lastName": "Schinner",
    "prisonName": "South Glamorgan (HMP)",
    "prisonerNumber": "1DULMVV",
    "religion": "Caries",
    "sentenceExpiryDate": "2037-09-04",
    "tariffDate": "2043-10-15"
  },
  {
    "bookingId": "1878518002",
    "conditionalReleaseDate": "2035-12-24",
    "dateOfBirth": "1988-3-8",
    "ethnicity": "Harum",
    "firstName": "Yvette",
    "gender": "Intersex person",
    "homeDetentionCurfewEligibilityDate": "2033-02-09",
    "lastName": "Stark",
    "paroleEligibilityDate": "2024-01-21",
    "prisonName": "Cumbria (HMP)",
    "prisonerNumber": "135A22I",
    "religion": "Tergo",
    "sentenceExpiryDate": "2036-01-08",
    "sentenceStartDate": "Thu Dec 25",
    "tariffDate": "2038-08-08"
  },
  {
    "bookingId": "9981350711",
    "conditionalReleaseDate": "2034-12-23",
    "dateOfBirth": "1969-3-26",
    "ethnicity": "Clam",
    "firstName": "Kavon",
    "gender": "Trans person",
    "indeterminateSentence": true,
    "lastName": "Labadie",
    "prisonName": "Norfolk (HMP)",
    "prisonerNumber": "JVWN4Y8",
    "religion": "Subnecto",
    "sentenceStartDate": "Sun Sep 18",
    "tariffDate": "2024-01-10"
  },
  {
    "bookingId": "5001303334",
    "conditionalReleaseDate": "2042-10-25",
    "dateOfBirth": "1980-1-30",
    "ethnicity": "Callide",
    "firstName": "Ronaldo",
    "gender": "Cis female",
    "homeDetentionCurfewEligibilityDate": "2042-09-05",
    "indeterminateSentence": false,
    "lastName": "Turner",
    "prisonName": "Tayside (HMP)",
    "prisonerNumber": "3CL85UT",
    "religion": "Accendo",
    "sentenceExpiryDate": "2043-10-29",
    "tariffDate": "2036-08-10"
  },
  {
    "bookingId": "9715401303",
    "dateOfBirth": "1961-2-3",
    "ethnicity": "Despecto",
    "firstName": "Diego",
    "gender": "Transexual woman",
    "homeDetentionCurfewEligibilityDate": "2036-04-04",
    "lastName": "Wisozk",
    "paroleEligibilityDate": "2029-02-10",
    "prisonName": "Suffolk (HMP)",
    "prisonerNumber": "UZB7W3A",
    "religion": "Cunae",
    "sentenceStartDate": "Sun Feb 11",
    "tariffDate": "2031-02-27"
  },
  {
    "bookingId": "9296270712",
    "conditionalReleaseDate": "2032-03-03",
    "dateOfBirth": "2002-11-7",
    "ethnicity": "Tepesco",
    "firstName": "Collin",
    "gender": "Intersex man",
    "homeDetentionCurfewEligibilityDate": "2034-10-19",
    "lastName": "Ernser",
    "paroleEligibilityDate": "2024-06-16",
    "prisonName": "Norfolk (HMP)",
    "prisonerNumber": "ZM5KTFH",
    "religion": "Aspernatur"
  },
  {
    "bookingId": "5855247541",
    "conditionalReleaseDate": "2025-09-04",
    "dateOfBirth": "1994-12-20",
    "ethnicity": "Surculus",
    "firstName": "Newton",
    "gender": "T* man",
    "homeDetentionCurfewEligibilityDate": "2027-07-19",
    "lastName": "Howe",
    "prisonName": "Humberside (HMP)",
    "prisonerNumber": "P0N4050",
    "religion": "Conculco",
    "sentenceExpiryDate": "2037-10-31",
    "sentenceStartDate": "Sun Jul 07",
    "tariffDate": "2028-11-01"
  },
  {
    "bookingId": "6460732428",
    "conditionalReleaseDate": "2030-11-09",
    "dateOfBirth": "1958-3-16",
    "ethnicity": "Arma",
    "firstName": "Corine",
    "gender": "Transexual male",
    "homeDetentionCurfewEligibilityDate": "2024-03-28",
    "indeterminateSentence": true,
    "lastName": "Cole",
    "paroleEligibilityDate": "2037-07-03",
    "prisonName": "Cleveland (HMP)",
    "prisonerNumber": "WMRXAKU",
    "religion": "Solium",
    "sentenceExpiryDate": "2028-04-27",
    "sentenceStartDate": "Fri Feb 01",
    "tariffDate": "2027-11-24"
  },
  {
    "bookingId": "1710334594",
    "conditionalReleaseDate": "2032-10-31",
    "dateOfBirth": "1976-7-18",
    "ethnicity": "Demitto",
    "firstName": "Rodolfo",
    "gender": "Agender",
    "homeDetentionCurfewEligibilityDate": "2032-11-30",
    "lastName": "Glover",
    "paroleEligibilityDate": "2041-05-26",
    "prisonName": "Fife (HMP)",
    "prisonerNumber": "XC1JMGC",
    "religion": "Candidus",
    "sentenceStartDate": "Sun Jun 04"
  },
  {
    "bookingId": "0352068923",
    "dateOfBirth": "1977-2-4",
    "ethnicity": "Ager",
    "firstName": "Ethelyn",
    "gender": "Trans male",
    "homeDetentionCurfewEligibilityDate": "2024-04-26",
    "indeterminateSentence": false,
    "lastName": "Rolfson",
    "paroleEligibilityDate": "2040-01-01",
    "prisonName": "Highlands and Islands (HMP)",
    "prisonerNumber": "C5OR3SQ",
    "religion": "Apud",
    "sentenceStartDate": "Fri Dec 09"
  },
  {
    "bookingId": "0314789716",
    "dateOfBirth": "1979-12-31",
    "ethnicity": "Brevis",
    "firstName": "Skylar",
    "gender": "Two* person",
    "homeDetentionCurfewEligibilityDate": "2032-11-05",
    "indeterminateSentence": false,
    "lastName": "Miller",
    "prisonName": "Berkshire (HMP)",
    "prisonerNumber": "XMHCORV",
    "religion": "Recusandae",
    "sentenceExpiryDate": "2041-06-27",
    "sentenceStartDate": "Thu Feb 28"
  },
  {
    "bookingId": "9848953220",
    "conditionalReleaseDate": "2041-03-12",
    "dateOfBirth": "1980-6-15",
    "ethnicity": "Rerum",
    "firstName": "Elza",
    "gender": "Trans person",
    "homeDetentionCurfewEligibilityDate": "2029-08-14",
    "lastName": "Blanda",
    "prisonName": "North Yorkshire (HMP)",
    "prisonerNumber": "AQ6V7KH",
    "religion": "Pecto",
    "sentenceExpiryDate": "2027-11-04",
    "sentenceStartDate": "Sun Aug 08",
    "tariffDate": "2036-07-22"
  },
  {
    "bookingId": "7742578281",
    "dateOfBirth": "1988-9-12",
    "ethnicity": "Accusamus",
    "firstName": "Alvah",
    "gender": "Female to male transsexual man",
    "indeterminateSentence": false,
    "lastName": "Langosh",
    "paroleEligibilityDate": "2037-12-07",
    "prisonName": "Grampian (HMP)",
    "prisonerNumber": "27LD9LP",
    "religion": "Amissio",
    "sentenceStartDate": "Thu Jan 02",
    "tariffDate": "2038-01-30"
  },
  {
    "bookingId": "7179581646",
    "conditionalReleaseDate": "2035-03-22",
    "dateOfBirth": "1968-12-28",
    "ethnicity": "Tego",
    "firstName": "Augustine",
    "gender": "Female to male trans man",
    "lastName": "Hauck",
    "paroleEligibilityDate": "2025-11-30",
    "prisonName": "Fife (HMP)",
    "prisonerNumber": "UJWXNSR",
    "religion": "Coruscus",
    "tariffDate": "2038-01-12"
  },
  {
    "bookingId": "5818749286",
    "dateOfBirth": "1977-11-13",
    "ethnicity": "Abduco",
    "firstName": "Evangeline",
    "gender": "Transmasculine",
    "homeDetentionCurfewEligibilityDate": "2039-02-15",
    "indeterminateSentence": false,
    "lastName": "Crooks",
    "prisonName": "Tayside (HMP)",
    "prisonerNumber": "I2T0T14",
    "religion": "Sophismata",
    "sentenceExpiryDate": "2034-03-27",
    "sentenceStartDate": "Tue Nov 21"
  },
  {
    "bookingId": "7217090509",
    "conditionalReleaseDate": "2037-10-14",
    "dateOfBirth": "1963-5-16",
    "ethnicity": "Est",
    "firstName": "Oswald",
    "gender": "Genderqueer",
    "indeterminateSentence": false,
    "lastName": "Wolff",
    "prisonName": "West Yorkshire (HMP)",
    "prisonerNumber": "CAECMFS",
    "religion": "Adfero",
    "sentenceExpiryDate": "2026-04-07",
    "tariffDate": "2040-11-04"
  },
  {
    "bookingId": "4382489101",
    "conditionalReleaseDate": "2031-07-14",
    "dateOfBirth": "1990-5-22",
    "ethnicity": "Decet",
    "firstName": "Kyra",
    "gender": "Pangender",
    "homeDetentionCurfewEligibilityDate": "2039-01-15",
    "indeterminateSentence": true,
    "lastName": "Kshlerin",
    "paroleEligibilityDate": "2032-11-29",
    "prisonName": "Rutland (HMP)",
    "prisonerNumber": "N24RBH2",
    "religion": "Canto",
    "sentenceExpiryDate": "2039-02-01",
    "tariffDate": "2033-01-10"
  },
  {
    "bookingId": "7577307753",
    "conditionalReleaseDate": "2032-08-26",
    "dateOfBirth": "2003-5-16",
    "ethnicity": "Ait",
    "firstName": "Rosalia",
    "gender": "Trans man",
    "homeDetentionCurfewEligibilityDate": "2028-03-19",
    "indeterminateSentence": false,
    "lastName": "Lehner",
    "paroleEligibilityDate": "2042-06-15",
    "prisonName": "Grampian (HMP)",
    "prisonerNumber": "W8CHFHM",
    "religion": "Blanditiis",
    "sentenceExpiryDate": "2028-11-08",
    "tariffDate": "2029-07-10"
  },
  {
    "bookingId": "8768910577",
    "conditionalReleaseDate": "2030-06-24",
    "dateOfBirth": "1975-9-6",
    "ethnicity": "Dolor",
    "firstName": "Dusty",
    "gender": "Intersex woman",
    "homeDetentionCurfewEligibilityDate": "2026-06-28",
    "indeterminateSentence": true,
    "lastName": "Von-Emard",
    "prisonName": "Suffolk (HMP)",
    "prisonerNumber": "FFVPDZL",
    "religion": "Vitium",
    "tariffDate": "2035-09-22"
  },
  {
    "bookingId": "8777318021",
    "conditionalReleaseDate": "2041-07-25",
    "dateOfBirth": "1979-6-26",
    "ethnicity": "Cicuta",
    "firstName": "Pansy",
    "gender": "Male to female trans woman",
    "homeDetentionCurfewEligibilityDate": "2026-02-04",
    "indeterminateSentence": true,
    "lastName": "Rath",
    "prisonName": "Gwent (HMP)",
    "prisonerNumber": "7GZYCT7",
    "religion": "Benevolentia",
    "sentenceStartDate": "Sat Sep 23",
    "tariffDate": "2028-02-01"
  },
  {
    "bookingId": "5979359583",
    "conditionalReleaseDate": "2034-06-22",
    "dateOfBirth": "1962-6-30",
    "ethnicity": "Desolo",
    "firstName": "Donny",
    "gender": "FTM",
    "lastName": "Koch",
    "prisonName": "Kent (HMP)",
    "prisonerNumber": "04P9F9E",
    "religion": "Usitas",
    "sentenceExpiryDate": "2041-03-31"
  },
  {
    "bookingId": "8920427213",
    "dateOfBirth": "1988-4-3",
    "ethnicity": "Amo",
    "firstName": "Clementina",
    "gender": "MTF",
    "indeterminateSentence": false,
    "lastName": "Bergstrom",
    "prisonName": "Dumfries and Galloway (HMP)",
    "prisonerNumber": "0T50F12",
    "religion": "Barba",
    "sentenceStartDate": "Wed Sep 09"
  },
  {
    "bookingId": "5320302280",
    "dateOfBirth": "1962-6-4",
    "ethnicity": "Artificiose",
    "firstName": "Ken",
    "gender": "Transgender person",
    "homeDetentionCurfewEligibilityDate": "2033-03-15",
    "lastName": "Veum-Krajcik",
    "prisonName": "Lincolnshire (HMP)",
    "prisonerNumber": "F0SRSJ8",
    "religion": "Virgo",
    "tariffDate": "2025-07-24"
  },
  {
    "bookingId": "9844726283",
    "conditionalReleaseDate": "2036-04-02",
    "dateOfBirth": "1952-9-24",
    "ethnicity": "Enim",
    "firstName": "Odessa",
    "gender": "Cisgender",
    "lastName": "Kulas",
    "prisonName": "Tayside (HMP)",
    "prisonerNumber": "HF1WH1L",
    "religion": "Vado"
  },
  {
    "bookingId": "8400551035",
    "dateOfBirth": "1952-3-22",
    "ethnicity": "Capillus",
    "firstName": "Ewald",
    "gender": "Trigender",
    "homeDetentionCurfewEligibilityDate": "2042-06-18",
    "indeterminateSentence": true,
    "lastName": "Jakubowski-Strosin",
    "paroleEligibilityDate": "2042-06-03",
    "prisonName": "Durham (HMP)",
    "prisonerNumber": "T5BR1XV",
    "religion": "Ascisco"
  },
  {
    "bookingId": "4300812300",
    "conditionalReleaseDate": "2033-03-04",
    "dateOfBirth": "1961-2-15",
    "ethnicity": "Sollers",
    "firstName": "Carlee",
    "gender": "Polygender",
    "homeDetentionCurfewEligibilityDate": "2027-08-07",
    "indeterminateSentence": false,
    "lastName": "Franey",
    "prisonName": "County Antrim (HMP)",
    "prisonerNumber": "UY1N011",
    "religion": "Ter"
  },
  {
    "bookingId": "9304192554",
    "conditionalReleaseDate": "2025-04-08",
    "dateOfBirth": "1985-1-19",
    "ethnicity": "Succurro",
    "firstName": "Zetta",
    "gender": "Gender questioning",
    "homeDetentionCurfewEligibilityDate": "2040-03-10",
    "indeterminateSentence": true,
    "lastName": "Champlin",
    "paroleEligibilityDate": "2031-10-19",
    "prisonName": "Cheshire (HMP)",
    "prisonerNumber": "AFZXD70",
    "religion": "Vilitas",
    "tariffDate": "2032-04-12"
  },
  {
    "bookingId": "8313939694",
    "conditionalReleaseDate": "2033-02-16",
    "dateOfBirth": "1946-8-14",
    "ethnicity": "Bellicus",
    "firstName": "Lesley",
    "gender": "Trigender",
    "homeDetentionCurfewEligibilityDate": "2034-04-29",
    "indeterminateSentence": true,
    "lastName": "Kohler",
    "prisonName": "Northumberland (HMP)",
    "prisonerNumber": "JTWZW2E",
    "religion": "Adflicto",
    "sentenceExpiryDate": "2036-01-28",
    "sentenceStartDate": "Thu Apr 10"
  },
  {
    "bookingId": "6260286581",
    "conditionalReleaseDate": "2025-07-12",
    "dateOfBirth": "1968-2-6",
    "ethnicity": "Umquam",
    "firstName": "Tyshawn",
    "gender": "Demiflux",
    "indeterminateSentence": false,
    "lastName": "Kassulke",
    "prisonName": "Kent (HMP)",
    "prisonerNumber": "ZRRCHJO",
    "religion": "Usque",
    "sentenceExpiryDate": "2039-09-03",
    "tariffDate": "2037-08-27"
  },
  {
    "bookingId": "9260795548",
    "dateOfBirth": "1952-7-9",
    "ethnicity": "Suadeo",
    "firstName": "Syble",
    "gender": "Gender questioning",
    "lastName": "Weber-Hackett",
    "prisonName": "Tyne and Wear (HMP)",
    "prisonerNumber": "USULN51",
    "religion": "Dedecor"
  },
  {
    "bookingId": "1545960492",
    "dateOfBirth": "1949-10-25",
    "ethnicity": "Ventosus",
    "firstName": "Lyric",
    "gender": "Transexual person",
    "indeterminateSentence": false,
    "lastName": "Dach",
    "prisonName": "East Sussex (HMP)",
    "prisonerNumber": "D124Z3L",
    "religion": "Carpo",
    "sentenceStartDate": "Sun Mar 26",
    "tariffDate": "2024-11-03"
  },
  {
    "bookingId": "9623195418",
    "conditionalReleaseDate": "2043-09-09",
    "dateOfBirth": "1957-3-7",
    "ethnicity": "Capto",
    "firstName": "Ford",
    "gender": "Transexual woman",
    "indeterminateSentence": true,
    "lastName": "Johnston",
    "paroleEligibilityDate": "2027-05-22",
    "prisonName": "Dorset (HMP)",
    "prisonerNumber": "4C59RIL",
    "religion": "Sint",
    "sentenceStartDate": "Wed Aug 16"
  },
  {
    "bookingId": "9793546830",
    "dateOfBirth": "1966-6-27",
    "ethnicity": "Provident",
    "firstName": "Garland",
    "gender": "Gender nonconforming",
    "homeDetentionCurfewEligibilityDate": "2037-04-27",
    "indeterminateSentence": true,
    "lastName": "Glover",
    "prisonName": "Hertfordshire (HMP)",
    "prisonerNumber": "GJNYGD6",
    "religion": "Tamquam",
    "sentenceExpiryDate": "2026-03-29"
  },
  {
    "bookingId": "5665464482",
    "dateOfBirth": "1945-4-27",
    "ethnicity": "Ea",
    "firstName": "Aylin",
    "gender": "Trigender",
    "homeDetentionCurfewEligibilityDate": "2035-02-11",
    "indeterminateSentence": false,
    "lastName": "Roberts",
    "paroleEligibilityDate": "2029-12-08",
    "prisonName": "Greater Manchester (HMP)",
    "prisonerNumber": "ENMP9SL",
    "religion": "Demergo",
    "sentenceStartDate": "Tue Mar 12"
  },
  {
    "bookingId": "7164710187",
    "conditionalReleaseDate": "2030-08-06",
    "dateOfBirth": "1970-4-16",
    "ethnicity": "Crastinus",
    "firstName": "Burnice",
    "gender": "FTM",
    "indeterminateSentence": false,
    "lastName": "Dickens",
    "prisonName": "West Midlands (HMP)",
    "prisonerNumber": "PELXHKC",
    "religion": "Thema",
    "sentenceStartDate": "Tue Feb 07"
  },
  {
    "bookingId": "1492245123",
    "conditionalReleaseDate": "2034-10-19",
    "dateOfBirth": "1975-6-16",
    "ethnicity": "Voluptatum",
    "firstName": "Jacquelyn",
    "gender": "Gender fluid",
    "indeterminateSentence": false,
    "lastName": "Blanda",
    "paroleEligibilityDate": "2026-04-21",
    "prisonName": "Hertfordshire (HMP)",
    "prisonerNumber": "HR1EQI2",
    "religion": "Sufficio",
    "sentenceExpiryDate": "2033-04-18",
    "tariffDate": "2033-03-29"
  },
  {
    "bookingId": "8858918087",
    "conditionalReleaseDate": "2036-09-02",
    "dateOfBirth": "1979-8-2",
    "ethnicity": "Tego",
    "firstName": "Breanne",
    "gender": "Multigender",
    "indeterminateSentence": true,
    "lastName": "Murphy-O'Keefe",
    "prisonName": "South Glamorgan (HMP)",
    "prisonerNumber": "YZ6RBNN",
    "religion": "Defessus",
    "sentenceExpiryDate": "2025-05-09",
    "sentenceStartDate": "Thu Nov 04",
    "tariffDate": "2033-04-06"
  },
  {
    "bookingId": "1647859489",
    "conditionalReleaseDate": "2038-08-22",
    "dateOfBirth": "2001-4-4",
    "ethnicity": "Sopor",
    "firstName": "Leland",
    "gender": "Cis male",
    "lastName": "Romaguera",
    "prisonName": "North Yorkshire (HMP)",
    "prisonerNumber": "A0O6ENK",
    "religion": "Coniecto",
    "sentenceStartDate": "Sat Nov 17",
    "tariffDate": "2041-12-04"
  },
  {
    "bookingId": "1448608882",
    "conditionalReleaseDate": "2041-07-11",
    "dateOfBirth": "1998-4-27",
    "ethnicity": "Veritas",
    "firstName": "Nelda",
    "gender": "Transexual woman",
    "indeterminateSentence": true,
    "lastName": "Walker",
    "prisonName": "County Antrim (HMP)",
    "prisonerNumber": "4CUT1G4",
    "religion": "Cognomen",
    "sentenceExpiryDate": "2024-11-02",
    "sentenceStartDate": "Sat Apr 02",
    "tariffDate": "2037-06-09"
  },
  {
    "bookingId": "6551340716",
    "dateOfBirth": "1983-6-2",
    "ethnicity": "Acquiro",
    "firstName": "Ruby",
    "gender": "Woman",
    "lastName": "Bruen",
    "paroleEligibilityDate": "2032-02-10",
    "prisonName": "Shropshire (HMP)",
    "prisonerNumber": "ZHL6G3M",
    "religion": "Totidem",
    "sentenceExpiryDate": "2029-11-07"
  },
  {
    "bookingId": "1630148371",
    "dateOfBirth": "1986-9-4",
    "ethnicity": "Viduo",
    "firstName": "Wilhelmine",
    "gender": "Gender fluid",
    "homeDetentionCurfewEligibilityDate": "2031-04-07",
    "indeterminateSentence": false,
    "lastName": "Wyman",
    "paroleEligibilityDate": "2033-04-05",
    "prisonName": "Surrey (HMP)",
    "prisonerNumber": "64CR2JR",
    "religion": "Eveniet",
    "sentenceExpiryDate": "2036-12-10",
    "sentenceStartDate": "Sat Oct 09",
    "tariffDate": "2039-08-16"
  },
  {
    "bookingId": "6213169552",
    "conditionalReleaseDate": "2032-05-19",
    "dateOfBirth": "1953-9-3",
    "ethnicity": "Solium",
    "firstName": "Leon",
    "gender": "Woman",
    "indeterminateSentence": false,
    "lastName": "Spencer",
    "prisonName": "Humberside (HMP)",
    "prisonerNumber": "YG0X5TO",
    "religion": "Culpo",
    "tariffDate": "2031-05-30"
  }
]
